examples/main.py
trey/__init__.py
trey/colors.py
trey/game_globals.py
trey/graphics.py
trey/image.py
trey/keyboard.py
trey/maths.py
trey/scene.py
trey/window.py
treyengine-0.0.1.dist-info/METADATA
treyengine-0.0.1.dist-info/WHEEL
treyengine-0.0.1.dist-info/licenses/LICENSE
treyengine-0.0.1.dist-info/RECORD
