Metadata-Version: 2.1
Name: TreyEngine
Version: 0.0.1
Summary: A small 2D game framework for Python
Project-URL: Homepage, https://github.com/Trey-Johnson3/TreyEngine
Author-email: Trey Johnson <treydog027@gmail.com>
License: MIT License
Classifier: License :: OSI Approved :: MIT License
Classifier: Operating System :: OS Independent
Classifier: Programming Language :: Python :: 3
Requires-Python: >=3.7
Requires-Dist: pysdl2-dll>=2.0.22
Requires-Dist: pysdl2>=0.9.13
